README.md
setup.py
generated_proto_pycode/DisplayedMessage_pb2.py
generated_proto_pycode/DisplayedMessage_pb2_grpc.py
generated_proto_pycode/Meta_pb2.py
generated_proto_pycode/Meta_pb2_grpc.py
generated_proto_pycode/OD2d_pb2.py
generated_proto_pycode/OD2d_pb2_grpc.py
generated_proto_pycode/OD3d_pb2.py
generated_proto_pycode/OD3d_pb2_grpc.py
generated_proto_pycode/__init__.py
generated_proto_pycode/common_pb2.py
generated_proto_pycode/common_pb2_grpc.py
generated_proto_pycode/helloworld_pb2.py
generated_proto_pycode/helloworld_pb2_grpc.py
generated_proto_pycode/service_pb2.py
generated_proto_pycode/service_pb2_grpc.py
generated_proto_pycode/validation_demo_pb2.py
generated_proto_pycode/validation_pb2.py
generated_proto_pycode/validation_pb2_grpc.py
lde_online_dep.egg-info/PKG-INFO
lde_online_dep.egg-info/SOURCES.txt
lde_online_dep.egg-info/dependency_links.txt
lde_online_dep.egg-info/top_level.txt